dworp/__init__.py
dworp/agent.py
dworp/environment.py
dworp/observer.py
dworp/plot.py
dworp/scheduling.py
dworp/simulation.py
dworp/space.py
dworp/time.py
dworp-0.1.0.dist-info/METADATA
dworp-0.1.0.dist-info/RECORD
dworp-0.1.0.dist-info/WHEEL
dworp-0.1.0.dist-info/top_level.txt
