Metadata-Version: 2.1
Name: dworp
Version: 0.1.0
Summary: Agent-based modeling framework
Home-page: https://github.com/ACI-ESP/dworp
Author: Cash Costello
Author-email: cash.costello@jhuapl.edu
License: BSD
Keywords: agents ABM modeling simulation agent-based
Platform: UNKNOWN
Classifier: Development Status :: 3 - Alpha
Classifier: Intended Audience :: Science/Research
Classifier: License :: OSI Approved :: BSD License
Classifier: Natural Language :: English
Classifier: Operating System :: OS Independent
Classifier: Programming Language :: Python :: 3 :: Only
Classifier: Topic :: Scientific/Engineering
Classifier: Topic :: Scientific/Engineering :: Artificial Life
Requires-Python: >=3.5
Provides-Extra: plot
Requires-Dist: numpy
Provides-Extra: plot
Requires-Dist: matplotlib; extra == 'plot'
